README
setup.py
ronpy/Git.py
ronpy/Shell.py
ronpy/Utils.py
ronpy/__init__.py
ronpy/ronpy.py
ronpy.egg-info/PKG-INFO
ronpy.egg-info/SOURCES.txt
ronpy.egg-info/dependency_links.txt
ronpy.egg-info/top_level.txt