Metadata-Version: 1.0
Name: ronpy
Version: 1.2.5
Summary: python libs
Home-page: https://gitee.com/rontian/ronpy
Author: rontian
Author-email: i@ronpad.com
License: MIT License
Keywords: ronpy
Platform: any
